Workbook

Sheet Capital and Depn
A3: ATTACHMENT D
A4: 2026 CAPITAL EXPENDITURE BUDGET
A5: Budget Assumptions:
A6: Exchange Rate | B6: =[1]Margins!B19 -> 0
A8: 2025 BUDGET
B9: Qty | C9: Amount (GH ¢) | D9: Amount US $) | E9: Amount US $) | F9: Estimated Volume | G9: IRR | H9: PAYBACK YRS | I9: RANKING
A10: A. CONSTRUCTION WORKS AT TDI AND SEK TERMINALS
A11: New fuel receipt line at the reclaimed land (log pond) | B11: 1 | C11: =D11*B6 -> 0
A12: Extension of TDH Office and Accessories | B12: 1 | C12: =D12*B6 -> 0
A13: Upgrade of Bondwalls -Sekondi Takoradi | B13: 1 | C13: =D13*B6 -> 0
A14: SUB TOTAL | C14: =SUM(C11:C13) -> 0
A16: B. TERMINAL AND OPERATIONAL EQUIPMENT
A17: Firefighting pipeline upgrade Takoradi | B17: 1 | C17: =D17*$B$6 -> 0 | F17: Introduction of stop valve after water tank
A18: Firefighting unit upgrade Sekondi | B18: 1 | C18: =D18*$B$6 -> 0
A19: Power and Comms Cable Restoration Takoradi | B19: 1 | C19: =D19*$B$6 -> 0
A20: Power and Comms Cable Restoration Sekondi | B20: 1 | C20: =D20*$B$6 -> 0
A21: TDH ATEC Light | B21: 1 | C21: =D21*$B$6 -> 0
A22: Yokogawa Systems Re-activation | B22: 1 | C22: =D22*$B$6 -> 0
A23: SNB SCADA System Software Upgrade | B23: 1 | C23: =D23*$B$6 -> 0
A24: 6 inch Receiving Hose (4x40m) | B24: 1 | C24: =D24*$B$6 -> 0
A25: SUB TOTAL | C25: =SUM(C17:C23) -> 0
A27: C. MOTOR VEHICLES
A29: L200 Pickup (4X4) | B29: 4 | C29: =D29*$B$6 -> 0
A30: i10 Hyundai | B30: 1 | C30: =D30*$B$6 -> 0
A31: SUB TOTAL | C31: =SUM(C28:C29) -> 0
A33: D. COMPUTERS & SOFTWARE
A34: Enterprise Systems (ERPs) | B34: 3 | C34: =D34*$B$6 -> 0 | F34: Sunsystems,
A35: Network Infrastructure | B35: 1 | C35: =D35*$B$6 -> 0 | F35: Server room upgrade with security
A36: Laser Printer | B36: 3 | C36: =D36*$B$6 -> 0 | F36: Heavy duty central office printer
A37: Laptop | B37: 10 | C37: =D37*$B$6 -> 0
A38: Access Control | B38: 1 | C38: =D38*$B$6 -> 0
A39: Desktop | B39: 4 | C39: =D39*$B$6 -> 0
A40: Computer Server | B40: 1 | C40: =D40*$B$6 -> 0 | F40: Rakes, Backup servers
A41: Scanners | B41: 5 | C41: =D41*$B$6 -> 0
A42: UPS Devices | B42: 10 | C42: =D42*$B$6 -> 0 | F42: confirm estimate
A43: SUB TOTAL | C43: =SUM(C34:C42) -> 0
A45: E. HSSE & QUALITY
A46: CCTV Upgrade | B46: 1 | C46: =D46*$B$6 -> 0 | F46: Upgrade of GOIL Exec. Center/Others
A47: HSSE ISO Certification | B47: 1 | C47: =D47*$B$6 -> 0
A48: Incident Reporting System | B48: 1
A49: CMP/IMS/ - implementation | B49: 1 | C49: =D49*$B$6 -> 0 | F49: ERP/IMS/Site Plans for the Group
A50: Intrinsically Safe Atex Camera/Explosion Proof Tablet | B50: 1 | C50: =D50*$B$6 -> 0
A51: Thickness Gauge Device | B51: 1 | C51: =D51*$B$6 -> 0
A52: SUB TOTAL | C52: =SUM(C46:C49) -> 0
A54: TOTALS | C54: =C52+C43+C31+C25+C14 -> 0
A56: ADD CONTINGENCY 5% | C56: =0.05*C54 -> 0
A58: GRAND TOTAL | C58: =C54+C56 -> 0
A60: Less: Cost of cable installation | C60: =C19+C20 -> 0
A62: Revised Capex | C62: =C58-C60 -> 0

Sheet Recurrent Expenses
A1: GOENERGY LIMITED | 2026 RECURRENT EXPENDITURE
A2: GOENERGY LIMITED
A3: 2026 RECURRENT EXPENDITURE BUDGET
B5: DESCRIPTION OF BUDGET ITEM | C5: 2026 BUDGET | D5: 2025 ACTUAL PROJECTION (LE) | E5: ACTUALS AS AT 30TH SEPT 2025 | F5: 2025 BUDGET | G5: 2025 PROJECTED vs 2025 BUDGET | H5: 2026 BUDGET vs 2025 PROJECTED
B6: 1. SALARIES AND ALLOWANCES
A7: 60601000 | B7: Normal Salaries
A8: 60600000 | B8: 13.0% Social Security Contribution
A9: 60610007 | B9: 10% PF
A10: 60610000 | B10: Annual Bonus | K10: =(C10-D10)/D10 -> #DIV/0!
A11: 60610006 | B11: 13th Mth Salary | J11: =(D11-F11)/F11 -> #DIV/0!
A12: 60601003 | B12: Other Allowances | J12: =(D12-F12)/F12 -> #DIV/0! | K12: =(C12-D12)/D12 -> #DIV/0!
A13: SUB TOTAL | B13: SUB -TOTAL
A14: 60601000 | B14: Contingency | J14: =(D14-F14)/F14 -> #DIV/0!
A15: SUB-TOTAL | B15: SUB -TOTAL | J15: =(D15-F15)/F15 -> #DIV/0!
B19: 2. DOMESTIC TRAVELLING & TRANSPORT
A20: 60801000 | B20: Travelling, Mission and Accommodation Expenses
A21: SUB-TOTAL | B21: SUB -TOTAL | I21: =SUM(I20:I20) -> 0
B23: 3. OTHER PERSONNEL COST
A24: 60804000 | B24: International Travels(Ticketing/Accommodation) | J24: =(D24-F24)/F24 -> #DIV/0! | K24: =(C24-D24)/D24 -> #DIV/0!
B25: Staff Training - External (Fees/Per diem) | J25: =(D25-F25)/F25 -> #DIV/0! | K25: =(C25-D25)/D25 -> #DIV/0!
B26: Other External Training (GOIL) | J26: =(D26-F26)/F26 -> #DIV/0! | K26: =(C26-D26)/D26 -> #DIV/0!
B27: External Business(local travel) | J27: =(D27-F27)/F27 -> #DIV/0! | K27: =(C27-D27)/D27 -> #DIV/0!
A28: 60901000 | B28: Staff Training Expenses (Local) | J28: =(D28-F28)/F28 -> #DIV/0! | K28: =(C28-D28)/D28 -> #DIV/0!
A29: *60607000 | B29: Medical Expenses | J29: =(D29-F29)/F29 -> #DIV/0! | K29: =(C29-D29)/D29 -> #DIV/0!
B30: Medical Examination (Yearly) | J30: =(D30-F30)/F30 -> #DIV/0! | K30: =(C30-D30)/D30 -> #DIV/0!
A31: 65300000 | B31: Head Office (Rent) | J31: =(D31-F31)/F31 -> #DIV/0! | K31: =(C31-D31)/D31 -> #DIV/0!
A32: 61601000 | B32: Laundry Expenses(Admin) | J32: =(D32-F32)/F32 -> #DIV/0! | K32: =(C32-D32)/D32 -> #DIV/0!
A33: 60612000 | B33: Subsidised Meals | J33: =(D33-F33)/F33 -> #DIV/0! | K33: =(C33-D33)/D33 -> #DIV/0!
A34: 6061000 | B34: End of Year Actvities/Long Service Award | J34: =(D34-F34)/F34 -> #DIV/0! | K34: =(C34-D34)/D34 -> #DIV/0!
A35: 60608000 | B35: Staff Welfare and Food Package (Admin)
A36: 60609001 | B36: Fitness & Recreation Assistance(Admin) | J36: =(D36-F36)/F36 -> #DIV/0! | K36: =(C36-D36)/D36 -> #DIV/0!
A37: SUB-TOTAL | B37: SUB -TOTAL
B39: 4. VARIOUS MATERIALS
A40: 60120001 | B40: Materials to warehouse | J40: =(D40-F40)/F40 -> #DIV/0! | K40: =(C40-D40)/D40 -> #DIV/0!
A41: 62300000 | B41: Stationery & Printing
A42: 62310000 | B42: Computer Forms and Accessories | J42: =(D42-F42)/F42 -> #DIV/0!
A43: 60609000 | B43: Uniform For Friday Wear | J43: =(D43-F43)/F43 -> #DIV/0! | K43: =(C43-D43)/D43 -> #DIV/0!
A44: SUB-TOTAL | B44: SUB -TOTAL
A46: 5. UTILITIES | B46: 5. UTILITIES
A47: 62401000 | B47: Electricity - Offices | J47: =(D47-F47)/F47 -> #DIV/0! | K47: =(C47-D47)/D47 -> #DIV/0!
A48: 62402000 | B48: Electricity -Houses | J48: =(D48-F48)/F48 -> #DIV/0! | K48: =(C48-D48)/D48 -> #DIV/0!
A49: 65102001 | B49: Electricity - Depots | J49: =(D49-F49)/F49 -> #DIV/0! | K49: =(C49-D49)/D49 -> #DIV/0!
A50: 62501000 | B50: Water - Offices | J50: =(D50-F50)/F50 -> #DIV/0! | K50: =(C50-D50)/D50 -> #DIV/0!
A51: 65102002 | B51: Water - Depots | J51: =(D51-F51)/F51 -> #DIV/0! | K51: =(C51-D51)/D51 -> #DIV/0!
A52: 62502000 | B52: Water - house | J52: =(D52-F52)/F52 -> #DIV/0!
A53: SUB-TOTAL | B53: SUB -TOTAL | J53: =(D53-F53)/F53 -> #DIV/0! | K53: =(C53-D53)/D53 -> #DIV/0!
A55: 6. MAINTENANCE & RUNNING COST | B55: 6. MAINTENANCE & RUNNING COST
A56: 60500000 | B56: Vehicle Maintenance | J56: =(D56-F56)/F56 -> #DIV/0! | K56: =(C56-D56)/D56 -> #DIV/0!
B57: Terminal Maintenance | J57: =(D57-F57)/F57 -> #DIV/0! | K57: =(C57-D57)/D57 -> #DIV/0!
A58: 60500004 | B58: Cost of Lubes consumed | J58: =(D58-F58)/F58 -> #DIV/0! | K58: =(C58-D58)/D58 -> #DIV/0!
A59: 60500005 | B59: Internal Consumption-Vehicle Fuel/Running Cost | J59: =(D59-F59)/F59 -> #DIV/0! | K59: =(C59-D59)/D59 -> #DIV/0!
A60: 61502000 | B60: Office Maintenance | J60: =(D60-F60)/F60 -> #DIV/0! | K60: =(C60-D60)/D60 -> #DIV/0!
A61: 61501000 | B61: General Office Equipment Mtce | J61: =(D61-F61)/F61 -> #DIV/0! | K61: =(C61-D61)/D61 -> #DIV/0!
A62: 61506000 | B62: Computer, Software & Network Mtce | J62: =(D62-F62)/F62 -> #DIV/0! | K62: =(C62-D62)/D62 -> #DIV/0!
A63: 61508000 | B63: Software License (ERP/Microsoft) etc | J63: =(D63-F63)/F63 -> #DIV/0! | K63: =(C63-D63)/D63 -> #DIV/0!
A64: 61503000 | B64: Executive House Mtce | J64: =(D64-F64)/F64 -> #DIV/0! | K64: =(C64-D64)/D64 -> #DIV/0!
A65: SUB-TOTAL | B65: SUB -TOTAL
B67: 7. VARIOUS SERVICES
A68: 65200000 | B68: Security & Other Services | J68: =(D68-F68)/F68 -> #DIV/0! | K68: =(C68-D68)/D68 -> #DIV/0!
A69: 60606000 | B69: Casual Labour | J69: =(D69-F69)/F69 -> #DIV/0! | K69: =(C69-D69)/D69 -> #DIV/0!
A70: 61504000 | B70: Janitorial and Ground Maintenance | J70: =(D70-F70)/F70 -> #DIV/0! | K70: =(C70-D70)/D70 -> #DIV/0!
A71: SUB-TOTAL | B71: SUB -TOTAL | J71: =(D71-F71)/F71 -> #DIV/0!
B73: 8. PROFESSIONAL SERVICE
A74: 60701000 | B74: Directors remuneration | J74: =(D74-F74)/F74 -> #DIV/0! | K74: =(C74-D74)/D74 -> #DIV/0!
A75: 60702000 | B75: Directors Other Expenses | J75: =(D75-F75)/F75 -> #DIV/0! | K75: =(C75-D75)/D75 -> #DIV/0!
A76: 61401000 | B76: Legal Expenses & Stamp Duty | J76: =(D76-F76)/F76 -> #DIV/0! | K76: =(C76-D76)/D76 -> #DIV/0!
A77: 61402000 | B77: Auditors Fees | J77: =(D77-F77)/F77 -> #DIV/0! | K77: =(C77-D77)/D77 -> #DIV/0!
A78: 651030 | B78: Quantity and Quality third party survey | J78: =(D78-F78)/F78 -> #DIV/0! | K78: =(C78-D78)/D78 -> #DIV/0!
A79: 61408000 | B79: Standard Authority & Statutory Inspection Fees(OM) | J79: =(D79-F79)/F79 -> #DIV/0! | K79: =(C79-D79)/D79 -> #DIV/0!
A80: 61404000 | B80: Various Professional & Technical Services
A81: 69100000 | B81: Stock Exchange Expenses | J81: =(D81-F81)/F81 -> #DIV/0! | K81: =(C81-D81)/D81 -> #DIV/0!
A82: 69200000 | B82: Annual General Meeting | J82: =(D82-F82)/F82 -> #DIV/0! | K82: =(C82-D82)/D82 -> #DIV/0!
A83: SUB-TOTAL | B83: SUB -TOTAL | J83: =(D83-F83)/F83 -> #DIV/0! | K83: =(C83-D83)/D83 -> #DIV/0!
B85: 9. TAXES/LEVIES/PERMITS
A86: 61604000FINHOF | B86: Acquisition of permits (EPA, NPA, etc) | J86: =(D86-F86)/F86 -> #DIV/0! | K86: =(C86-D86)/D86 -> #DIV/0!
A87: 65202002 | B87: Property rates | J87: =(D87-F87)/F87 -> #DIV/0! | K87: =(C87-D87)/D87 -> #DIV/0!
A88: 61604000 | B88: Vehicle Licence/Rd. Worthy | J88: =(D88-F88)/F88 -> #DIV/0! | K88: =(C88-D88)/D88 -> #DIV/0!
A89: SUB-TOTAL | B89: SUB -TOTAL | J89: =(D89-F89)/F89 -> #DIV/0! | K89: =(C89-D89)/D89 -> #DIV/0!
B91: 10. EQUIPMENT HIRING & RENTAL
A92: 65300001 | B92: Building Rents / Offices | J92: =(D92-F92)/F92 -> #DIV/0! | K92: =(C92-D92)/D92 -> #DIV/0!
A93: 61603000 | B93: Equipment hiring | J93: =(D93-F93)/F93 -> #DIV/0! | K93: =(C93-D93)/D93 -> #DIV/0!
A94: 60611000 | B94: Courier & Dispatch/Tel | J94: =(D94-F94)/F94 -> #DIV/0! | K94: =(C94-D94)/D94 -> #DIV/0!
A95: SUB-TOTAL | B95: SUB -TOTAL
B97: 11. INSURANCE PREMIUM
A98: 61101000 | B98: Fire & Burglary | J98: =(D98-F98)/F98 -> #DIV/0! | K98: =(C98-D98)/D98 -> #DIV/0!
A99: 61103000 | B99: Vehicle Insurance | J99: =(D99-F99)/F99 -> #DIV/0! | K99: =(C99-D99)/D99 -> #DIV/0!
A100: 61106000 | B100: Product at Depots | J100: =(D100-F100)/F100 -> #DIV/0! | K100: =(C100-D100)/D100 -> #DIV/0!
A101: 61108000 | B101: Directors Indemnity | J101: =(D101-F101)/F101 -> #DIV/0! | K101: =(C101-D101)/D101 -> #DIV/0!
A102: 61102000 | B102: Group Personal Accident-covered | J102: =(D102-F102)/F102 -> #DIV/0! | K102: =(C102-D102)/D102 -> #DIV/0!
A103: 61109001 | B103: Group Life Insurance (Comprehensive) | J103: =(D103-F103)/F103 -> #DIV/0! | K103: =(C103-D103)/D103 -> #DIV/0!
A104: SUB-TOTAL | B104: SUB -TOTAL | K104: =(C104-D104)/D104 -> #DIV/0!
B106: 12. SALES PROMOTION & ADVERTISING
A107: 61301000 | B107: Advertising
A108: 61303000 | B108: Seasonal/end-of-year promotions
A109: 61302000 | B109: Sales & business promotion
B110: SUB -TOTAL | I110: =SUM(I107:I109) -> 0
B112: 13. OTHER COSTS
A113: 62700000 | B113: Subscriptions | J113: =(D113-F113)/F113 -> #DIV/0! | K113: =(C113-D113)/D113 -> #DIV/0!
A114: 62100000 | B114: Specific Charity / Sponsorship | J114: =(D114-F114)/F114 -> #DIV/0! | K114: =(C114-D114)/D114 -> #DIV/0!
A115: 62800000 | B115: Donations | J115: =(D115-F115)/F115 -> #DIV/0! | K115: =(C115-D115)/D115 -> #DIV/0!
...

Sheet Volumes
B2: ATTACHMENT A
B4: 2026 BUDGET - VOLUMES
B5: PRODUCT | C5: MONTHLY 2026 Sales Volume | D5: 2026 Budget Volume of Sales | E5: 2025 Projected Sales | F5: 2025 Budget Volume of Sales | G5: % of 2026 Budget sales over 2025 Projected | H5: % of 2025 projected sales over 2025 Budgeted | I5: As at 30 SEP 2025 | J5: 2024 Actual | K5: 2023 Actuals | L5: 2022 Actuals | M5: 2021 Actuals
B6: GASOLINE (PMS)
B7: GASOIL (AGO)
B8: MARINE GASOIL-LOCAL
B9: MARINE GASOIL -RIG & FOREIGN
B10: AGO EXPORT
B11: AGO MINES
B12: JET A1
B13: HFO
B14: Total
B15: LPGas /Kg
C16: 2023 | D16: 2021
C17: =E6/12 -> 0 | D17: =L6/12 -> 0 | E17: =K6/12 -> 0
C18: =E7/12 -> 0 | D18: =L7/12 -> 0 | E18: =K7/12 -> 0
C19: =E8/12 -> 0 | D19: =L8/12 -> 0 | E19: =K8/12 -> 0
C20: =E9/12 -> 0 | D20: =L9/12 -> 0 | E20: =K9/12 -> 0
C21: =E10/12 -> 0 | D21: =L10/12 -> 0 | E21: =K10/12 -> 0
C22: =E11/12 -> 0 | D22: =L11/12 -> 0 | E22: =K11/12 -> 0
C23: =E12/12 -> 0 | D23: =L12/12 -> 0 | E23: =K12/12 -> 0
C24: =E13/12 -> 0 | D24: =L13/12 -> 0 | E24: =K13/12 -> 0
C25: =E14/12 -> 0 | D25: =L14/12 -> 0 | E25: =K14/12 -> 0
A28: Quarterly Sales
B29: Seasonal Sales
B30: Monthly Sales Volume Proportion to Annual | C30: Jan | D30: Feb | E30: Mar | F30: Apr | G30: May | H30: Jun | I30: Jul | J30: Aug | K30: Sep | L30: Oct | M30: Nov | N30: Dec | O30: Total
B31: Gasoline PMS 95 | C31: 0.11185098 | D31: 0.095858152 | E31: 0.10523399 | F31: 0.092224317 | G31: 0.077466102 | H31: 0.081967024 | I31: 0.065319029 | J31: 0.072052852 | K31: 0.076718667 | L31: 0.06705606 | M31: 0.086287176 | N31: 0.06796565 | O31: =SUM(C31:N31) -> 1
B32: Gasoil | C32: 0.099057363 | D32: 0.08385157 | E32: 0.10102058 | F32: 0.091173134 | G32: 0.092694401 | H32: 0.072821749 | I32: 0.087075636 | J32: 0.071625555 | K32: 0.073278311 | L32: 0.072115598 | M32: 0.078913817 | N32: 0.076372285 | O32: =SUM(C32:N32) -> 1
B33: MGO Local | C33: 0.017216759 | D33: 0.012153006 | E33: 0.081308789 | F33: 0.023293262 | G33: 0.048612025 | H33: 0.05772678 | I33: 0.035952644 | J33: 0.011646631 | K33: 0.097224051 | L33: 0.4128266 | M33: 0.18380994 | N33: 0.01822951 | O33: =SUM(C33:N33) -> 1
B34: MGO Foreign | C34: 0.06091089 | D34: 0.035810113 | E34: 0.081557583 | F34: 0.10826823 | G34: 0.1221565 | H34: 0.10053692 | I34: 0.10671478 | J34: 0.057833242 | K34: 0.098450184 | L34: 0.083889964 | M34: 0.078217065 | N34: 0.065654522 | O34: =SUM(C34:N34) -> 1
B35: AGO Export | C35: 0.08 | D35: 0.09 | E35: 0.08 | F35: 0.07 | G35: 0.08 | H35: 0.1 | I35: 0.07 | J35: 0.09 | K35: 0.07 | L35: 0.08 | M35: 0.08 | N35: 0.11 | O35: =SUM(C35:N35) -> 1
B36: AGO Mines | C36: 0.056523364 | D36: 0.092261682 | E36: 0.088971963 | F36: 0.094280374 | G36: 0.10676636 | H36: 0.076785047 | I36: 0.065046729 | J36: 0.074242991 | K36: 0.073495327 | L36: 0.081869159 | M36: 0.10063551 | N36: 0.089121495 | O36: =SUM(C36:N36) -> 1
B37: ATK | C37: 0.10795554 | D37: 0.11080724 | E37: 0.16396106 | F37: 0.050621569 | G37: 0.066422792 | H37: 0.085001695 | I37: 0.061171301 | J37: 0.067268173 | K37: 0.059472747 | L37: 0.1046792 | M37: 0.066500707 | N37: 0.056137972 | O37: =SUM(C37:N37) -> 1
B38: LPG | C38: 0.065531955 | D38: 0.058612946 | E38: 0.069440898 | F38: 0.072793034 | G38: 0.077741373 | H38: 0.079926402 | I38: 0.096504372 | J38: 0.1042584 | K38: 0.074789228 | L38: 0.091443486 | M38: 0.10395325 | N38: 0.10500465 | O38: =SUM(C38:N38) -> 1
C40: Jan | D40: Feb | E40: Mar | F40: Apr | G40: May | H40: Jun | I40: Jul | J40: Aug | K40: Sep | L40: Oct | M40: Nov | N40: Dec | O40: Total
B41: Gasoline PMS 95 | C41: =C31*$D$6 -> 0 | D41: =D31*$D$6 -> 0 | E41: =E31*$D$6 -> 0 | F41: =F31*$D$6 -> 0 | G41: =G31*$D$6 -> 0 | H41: =H31*$D$6 -> 0 | I41: =I31*$D$6 -> 0 | J41: =J31*$D$6 -> 0 | ... N41: =N31*$D$6 -> 0 | O41: =SUM(C41:N41) -> 0
B42: Gasoil | C42: =C32*$D$7 -> 0 | D42: =D32*$D$7 -> 0 | E42: =E32*$D$7 -> 0 | F42: =F32*$D$7 -> 0 | G42: =G32*$D$7 -> 0 | H42: =H32*$D$7 -> 0 | I42: =I32*$D$7 -> 0 | J42: =J32*$D$7 -> 0 | ... N42: =N32*$D$7 -> 0 | O42: =SUM(C42:N42) -> 0
B43: MGO Local | C43: =C33*$D$8 -> 0 | D43: =D33*$D$8 -> 0 | E43: =E33*$D$8 -> 0 | F43: =F33*$D$8 -> 0 | G43: =G33*$D$8 -> 0 | H43: =H33*$D$8 -> 0 | I43: =I33*$D$8 -> 0 | J43: =J33*$D$8 -> 0 | ... N43: =N33*$D$8 -> 0 | O43: =SUM(C43:N43) -> 0
B44: MGO Foreign | C44: =C34*$D$9 -> 0 | D44: =D34*$D$9 -> 0 | E44: =E34*$D$9 -> 0 | F44: =F34*$D$9 -> 0 | G44: =G34*$D$9 -> 0 | H44: =H34*$D$9 -> 0 | I44: =I34*$D$9 -> 0 | J44: =J34*$D$9 -> 0 | ... N44: =N34*$D$9 -> 0 | O44: =SUM(C44:N44) -> 0
B45: AGO Export | C45: =C35*$D$10 -> 0 | D45: =D35*$D$10 -> 0 | E45: =E35*$D$10 -> 0 | F45: =F35*$D$10 -> 0 | G45: =G35*$D$10 -> 0 | H45: =H35*$D$10 -> 0 | I45: =I35*$D$10 -> 0 | J45: =J35*$D$10 -> 0 | ... N45: =N35*$D$10 -> 0 | O45: =SUM(C45:N45) -> 0
B46: AGO Mines | C46: =C36*$D$11 -> 0 | D46: =D36*$D$11 -> 0 | E46: =E36*$D$11 -> 0 | F46: =F36*$D$11 -> 0 | G46: =G36*$D$11 -> 0 | H46: =H36*$D$11 -> 0 | I46: =I36*$D$11 -> 0 | J46: =J36*$D$11 -> 0 | ... N46: =N36*$D$11 -> 0 | O46: =SUM(C46:N46) -> 0
B47: ATK | C47: =C37*$D$12 -> 0 | D47: =D37*$D$12 -> 0 | E47: =E37*$D$12 -> 0 | F47: =F37*$D$12 -> 0 | G47: =G37*$D$12 -> 0 | H47: =H37*$D$12 -> 0 | I47: =I37*$D$12 -> 0 | J47: =J37*$D$12 -> 0 | ... N47: =N37*$D$12 -> 0 | O47: =SUM(C47:N47) -> 0
B48: LPG | C48: =C38*$D$15 -> 0 | D48: =D38*$D$15 -> 0 | E48: =E38*$D$15 -> 0 | F48: =F38*$D$15 -> 0 | G48: =G38*$D$15 -> 0 | H48: =H38*$D$15 -> 0 | I48: =I38*$D$15 -> 0 | J48: =J38*$D$15 -> 0 | ... N48: =N38*$D$15 -> 0 | O48: =SUM(C48:N48) -> 0
B49: Total | O49: =SUM(O41:O48) -> 0
B52: Sales Volume | C52: 2026 Q1 | D52: 2026 Q2 | E52: 2026 Q3 | F52: 2026 Q4 | G52: Total
B53: Gasoline PMS 95 | C53: =SUM(Volumes!C41:E41) -> 0 | D53: =SUM(Volumes!F41:H41) -> 0 | E53: =SUM(Volumes!I41:K41) -> 0 | F53: =SUM(Volumes!L41:N41) -> 0 | G53: =SUM(C53:F53) -> 0
B54: Gasoil | C54: =SUM(Volumes!C42:E42) -> 0 | D54: =SUM(Volumes!F42:H42) -> 0 | E54: =SUM(Volumes!I42:K42) -> 0 | F54: =SUM(Volumes!L42:N42) -> 0 | G54: =SUM(C54:F54) -> 0
B55: MGO Local | C55: =SUM(Volumes!C43:E43) -> 0 | D55: =SUM(Volumes!F43:H43) -> 0 | E55: =SUM(Volumes!I43:K43) -> 0 | F55: =SUM(Volumes!L43:N43) -> 0 | G55: =SUM(C55:F55) -> 0
B56: MGO Foreign | C56: =SUM(Volumes!C44:E44) -> 0 | D56: =SUM(Volumes!F44:H44) -> 0 | E56: =SUM(Volumes!I44:K44) -> 0 | F56: =SUM(Volumes!L44:N44) -> 0 | G56: =SUM(C56:F56) -> 0
B57: AGO Export | C57: =SUM(Volumes!C45:E45) -> 0 | D57: =SUM(Volumes!F45:H45) -> 0 | E57: =SUM(Volumes!I45:K45) -> 0 | F57: =SUM(Volumes!L45:N45) -> 0 | G57: =SUM(C57:F57) -> 0
B58: AGO Mines | C58: =SUM(Volumes!C46:E46) -> 0 | D58: =SUM(Volumes!F46:H46) -> 0 | E58: =SUM(Volumes!I46:K46) -> 0 | F58: =SUM(Volumes!L46:N46) -> 0 | G58: =SUM(C58:F58) -> 0
B59: ATK | C59: =SUM(Volumes!C47:E47) -> 0 | D59: =SUM(Volumes!F47:H47) -> 0 | E59: =SUM(Volumes!I47:K47) -> 0 | F59: =SUM(Volumes!L47:N47) -> 0 | G59: =SUM(C59:F59) -> 0
B60: LPG | C60: =SUM(Volumes!C48:E48) -> 0 | D60: =SUM(Volumes!F48:H48) -> 0 | E60: =SUM(Volumes!I48:K48) -> 0 | F60: =SUM(Volumes!L48:N48) -> 0 | G60: =SUM(C60:F60) -> 0
B61: Total | C61: =SUM(C53:C60) -> 0 | D61: =SUM(D53:D60) -> 0 | E61: =SUM(E53:E60) -> 0 | F61: =SUM(F53:F60) -> 0 | G61: =SUM(G53:G60) -> 0

Sheet Dep sche
A2: Capital Expenditure GHS'000 | B2: 2024 Budget | C2: 45352 | D2: 45444 | E2: 45536 | F2: 45627
A3: Construction of New Depot/Land Preparation | B3: =21000*1000 -> 21000000 | C3: =B3/4 -> 5250000 | D3: =C3 -> 5250000 | E3: =D3 -> 5250000 | F3: =E3 -> 5250000
A4: Rehabilation of Head Office E-Centre | B4: =5400*1000 -> 5400000 | C4: =B4/4 -> 1350000 | D4: =C4 -> 1350000 | E4: =D4 -> 1350000 | F4: =E4 -> 1350000
A5: Terminal and Operational Equipment | B5: =14886.66045*1000 -> 14886660 | C5: =B5/4 -> 3721665.1 | D5: =C5 -> 3721665.1 | E5: =D5 -> 3721665.1 | F5: =E5 -> 3721665.1
A6: Motor Vehicles | B6: =8281.25*1000 -> 8281250 | C6: =B6/4 -> 2070312.5 | D6: =C6 -> 2070312.5 | E6: =D6 -> 2070312.5 | F6: =E6 -> 2070312.5
A7: Office & Household Equipment | B7: =1120*1000 -> 1120000 | C7: =B7/4 -> 280000 | D7: =C7 -> 280000 | E7: =D7 -> 280000 | F7: =E7 -> 280000
A8: Computers & Software | B8: =4053.125*1000 -> 4053125 | C8: =B8/4 -> 1013281.2 | D8: =C8 -> 1013281.2 | E8: =D8 -> 1013281.2 | F8: =E8 -> 1013281.2
A9: HSSE & Quality | B9: =2750*1000 -> 2750000 | C9: =B9/4 -> 687500 | D9: =C9 -> 687500 | E9: =D9 -> 687500 | F9: =E9 -> 687500
A10: Sub-Total | B10: =SUM(B3:B9) -> 57491035 | C10: =B10/4 -> 14372759 | D10: =C10 -> 14372759 | E10: =D10 -> 14372759 | F10: =E10 -> 14372759
A11: Contigencies | B11: =5%*B10 -> 2874551.8 | C11: =B11/4 -> 718637.94 | D11: =C11 -> 718637.94 | E11: =D11 -> 718637.94 | F11: =E11 -> 718637.94
A12: Total | B12: =SUM(B10:B11) -> 60365587 | C12: =SUM(C10:C11) -> 15091397 | D12: =SUM(D10:D11) -> 15091397 | E12: =SUM(E10:E11) -> 15091397 | F12: =SUM(F10:F11) -> 15091397
A15: Capital Expenditure GHS'000 | B15: 2026 Budget | C15: 46082 | D15: 46174 | E15: 46266 | F15: 46357
A16: CONSTRUCTION WORKS AT TDI AND SEK TERMINALS
A17: TERMINAL AND OPERATIONAL EQUIPMENT
A18: MOTOR VEHICLES
A19: COMPUTERS & SOFTWARE
A20: HSSE & QUALITY
A21: Sub-Total
A22: Contigencies
A23: Total

Sheet Purchases
A2: ATTACHMENT A
A4: 2026 BUDGET - PURCHASES
A5: PRODUCT | B5: MONTHLY | C5: 2026 BUDGET SALES VOLUME | D5: FACTOR | E5: MONTHLY MT | F5: UNIT FOB COST $/MT | G5: SUPPLIERS PREMIUM | H5: CBM CHARGES | I5: STORAGE AND RACK LOADING | J5: PORT RELATED CHARGES | K5: ESCALATION AND DEESCALATION | L5: TOTAL COST OF SALE $/MT | M5: MONTHLY FOB PURCHASES | N5: ANNUAL COST OF SALE | O5: MONTHLY COST OF SALE
A6: GASOLINE (PMS) | B6: =[1]Volumes!C6 -> 0 | C6: =12*B6 -> 0 | O6: =E6*L6 -> 0 | R6: =150000/16.5 -> 9090.9091 | S6: =17000*16.5 -> 280500
A7: GASOIL (AGO) | B7: =[1]Volumes!C7 -> 0 | C7: =B7*12 -> 0 | O7: =E7*L7 -> 0
A8: MARINE GASOIL-LOCAL | B8: =[1]Volumes!C8 -> 0 | C8: =12*B8 -> 0 | O8: =E8*L8 -> 0
A9: MARINE GASOIL -RIG & FOREIGN | B9: =[1]Volumes!C9 -> 0 | C9: =12*B9 -> 0 | O9: =E9*L9 -> 0
A10: AGO EXPORT | B10: =[1]Volumes!C10 -> 0 | C10: =12*B10 -> 0 | O10: =E10*L10 -> 0
A11: AGO MINES | B11: =[1]Volumes!C11 -> 0 | C11: =12*B11 -> 0 | O11: =E11*L11 -> 0
A12: JET A1 | B12: =[1]Volumes!C12 -> 0 | C12: =12*B12 -> 0 | O12: =E12*L12 -> 0
A13: HFO | B13: =[1]Volumes!C13 -> 0 | C13: =12*B13 -> 0 | L13: =SUM(F13:K13) -> 0
A14: Total | B14: =SUM(B6:B13) -> 0 | C14: =SUM(C6:C13)-C13 -> 0 | L14: =SUM(F14:K14) -> 0 | M14: =SUM(M6:M13) -> 0 | N14: =SUM(N6:N13) -> 0 | O14: =SUM(O6:O13) -> 0
A15: LPGas /Kg | B15: =[1]Volumes!C15 -> 0 | C15: =12*B15 -> 0
N16: =SUM(N14:N15) -> 0 | O16: =SUM(O14:O15) -> 0
N17: ANNUALLY | O17: MONTHLY
A18: We assume prices will go up by 5% | M18: GHS | N18: =N16*14.5 -> 0 | O18: =O16*14.5 -> 0
A19: EIA 2026
A20: EIA 22025 | N20: =785394935.34-N16 -> 7.8539494e+08 | O20: =N20/N16 -> #DIV/0!
A21: GROWTH | N21: =N20*14.5 -> 1.1388227e+10
A25: Quarterly Cost of Sales
A30: 2025 Q4 Budgeted Purchases
A31: PRODUCT | B31: Q4 2025 | C31: Q4 Budgeted Monthly Sales Volume | D31: FACTOR | E31: MONTHLY MT | F31: UNIT FOB COST $/MT | G31: Suppliers Premium | H31: cbm charges | I31: Storage and rack loading | J31: Port related charges | K31: Escalation and deescalation | L31: Total Cost of Sale $/MT | M31: MONTHLY FOB PURCHASES | N31: Q4 COST OF SALES | O31: MONTHLY COST OF SALE
A32: GASOLINE (PMS) | B32: =[1]Volumes!E6-[1]Volumes!I6 -> 0 | C32: =B32/3 -> 0 | D32: 1342.503 | E32: =C32/D32 -> 0 | F32: =860*1.05 -> 903 | G32: 105 | H32: 9 | I32: =12*1.185 -> 14.22 | J32: =3.5+5+2.9 -> 11.4 | K32: 15 | L32: =F33+G32+H32+I32+J32+K32 -> 1057.62 | M32: =F33*E32 -> 0 | N32: =E32*3*L32 -> 0 | O32: =E32*L32/3 -> 0
A33: GASOIL (AGO) | B33: =[1]Volumes!E7-[1]Volumes!I7 -> 0 | C33: =B33/3 -> 0 | D33: 1183.432 | E33: =C33/D33 -> 0 | F33: =860*1.05 -> 903 | G33: 105 | H33: 9 | I33: =12*1.185 -> 14.22 | J33: =3.5+5+2.9 -> 11.4 | K33: 15 | L33: =F34+G33+H33+I33+J33+K33 -> 1046.94 | M33: =F34*E33 -> 0 | N33: =E33*3*L33 -> 0 | O33: =E33*L33/3 -> 0
A34: MARINE GASOIL-LOCAL | B34: =[1]Volumes!E8-[1]Volumes!I8 -> 0 | C34: =B34/3 -> 0 | D34: 1183.432 | E34: =C34/D34 -> 0 | F34: =858*1.04 -> 892.32 | G34: 105 | H34: 9 | I34: =12*1.185 -> 14.22 | J34: =3.5+5+2.9 -> 11.4 | K34: 15 | L34: =F35+G34+H34+I34+J34+K34 -> 1046.94 | M34: =F35*E34 -> 0 | N34: =E34*3*L34 -> 0 | O34: =E34*L34/3 -> 0
A35: MARINE GASOIL -RIG & FOREIGN | B35: =[1]Volumes!E9-[1]Volumes!I9 -> 0 | C35: =B35/3 -> 0 | D35: 1183.432 | E35: =C35/D35 -> 0 | F35: =858*1.04 -> 892.32 | G35: 105 | H35: 9 | I35: =12*1.185 -> 14.22 | J35: =3.5+5+2.9 -> 11.4 | K35: 15 | L35: =F36+G35+H35+I35+J35+K35 -> 1046.94 | M35: =F36*E35 -> 0 | N35: =E35*3*L35 -> 0 | O35: =E35*L35/3 -> 0
A36: AGO EXPORT | B36: =[1]Volumes!E10-[1]Volumes!I10 -> 0 | C36: =B36/3 -> 0 | D36: 1183.432 | E36: =C36/D36 -> 0 | F36: =858*1.04 -> 892.32 | G36: 105 | H36: 9 | I36: =12*1.185 -> 14.22 | J36: =3.5+5+2.9 -> 11.4 | K36: 15 | L36: =F37+G36+H36+I36+J36+K36 -> 1046.94 | M36: =F37*E36 -> 0 | N36: =E36*3*L36 -> 0 | O36: =E36*L36/3 -> 0
A37: AGO MINES | B37: =[1]Volumes!E11-[1]Volumes!I11 -> 0 | C37: =B37/3 -> 0 | D37: 1183.432 | E37: =C37/D37 -> 0 | F37: =858*1.04 -> 892.32 | G37: 105 | H37: 9 | I37: =12*1.185 -> 14.22 | J37: =3.5+5+2.9 -> 11.4 | K37: 15 | L37: =F38+G37+H37+I37+J37+K37 -> 1046.94 | M37: =F38*E37 -> 0 | N37: =E37*3*L37 -> 0 | O37: =E37*L37/3 -> 0
A38: JET A1 | B38: =[1]Volumes!E12-[1]Volumes!I12 -> 0 | C38: =B38/3 -> 0 | D38: 1241 | E38: =C38/D38 -> 0 | F38: =858*1.04 -> 892.32 | G38: 105 | H38: 9 | I38: =12*1.185 -> 14.22 | J38: =3.5+5+2.9 -> 11.4 | K38: 15 | L38: =F39+G38+H38+I38+J38+K38 -> 154.62 | N38: =E38*3*L38 -> 0 | O38: =E38*L38/3 -> 0
A39: HFO | B39: =[1]Volumes!E13-[1]Volumes!I13 -> 0 | C39: =12*B39 -> 0
A40: Total | B40: 0 | C40: =SUM(C32:C39)-C39 -> 0 | M40: =SUM(M32:M39) -> 0 | N40: =SUM(N32:N39) -> 0 | O40: =SUM(O32:O39) -> 0
A41: LPGas /Kg | B41: =[1]Volumes!E15-[1]Volumes!I15 -> 0 | C41: =B41/3 -> 0 | D41: 1000 | E41: =C41/D41 -> 0 | F41: =827*1.04 -> 860.08 | G41: 105 | H41: 9 | I41: =12*1.185 -> 14.22 | J41: =3.5+5+2.9 -> 11.4 | K41: 15 | L41: =F42+G41+H41+I41+J41+K41 -> 154.62 | M41: =E41*F42 -> 0 | N41: =E41*3*L41 -> 0 | O41: =E41*L41/3 -> 0
N42: =SUM(N40:N41) -> 0 | O42: =SUM(O40:O41) -> 0
N43: ANNUALLY | O43: MONTHLY
A44: We assume prices will go up by 5% | M44: GHS | N44: =N42*14.5 -> 0 | O44: =O42*14.5 -> 0
N59: 7.8539494e+08
A60: Conversion Factor | B60: 2026 Q1 | C60: 2026 Q2 | D60: 2026 Q3 | E60: 2026 Q4
A61: Gasoline PMS 95 | B61: =Purchases!D6 -> 0 | C61: =B61 -> 0 | D61: =C61 -> 0 | E61: =D61 -> 0
A62: Gasoil | B62: =Purchases!D7 -> 0 | C62: =B62 -> 0 | D62: =C62 -> 0 | E62: =D62 -> 0
A63: MGO Local | B63: =Purchases!D8 -> 0 | C63: =B63 -> 0 | D63: =C63 -> 0 | E63: =D63 -> 0
A64: MGO Foreign | B64: =Purchases!D9 -> 0 | C64: =B64 -> 0 | D64: =C64 -> 0 | E64: =D64 -> 0
A65: AGO Export | B65: =Purchases!D10 -> 0 | C65: =B65 -> 0 | D65: =C65 -> 0 | E65: =D65 -> 0
A66: AGO Mines | B66: =Purchases!D11 -> 0 | C66: =B66 -> 0 | D66: =C66 -> 0 | E66: =D66 -> 0
A67: ATK | B67: =Purchases!D12 -> 0 | C67: =B67 -> 0 | D67: =C67 -> 0 | E67: =D67 -> 0
A68: LPG | B68: =Purchases!D15 -> 0 | C68: =B68 -> 0 | D68: =C68 -> 0 | E68: =D68 -> 0
A71: TOTAL COST OF SALE $/MT | B71: 2026 Q1 | C71: 2026 Q2 | D71: 2026 Q3 | E71: 2026 Q4
A72: Gasoline PMS 95 | B72: =Purchases!L6 -> 0 | C72: =B72 -> 0 | D72: =C72 -> 0 | E72: =D72 -> 0
A73: Gasoil | B73: =Purchases!L7 -> 0 | C73: =B73 -> 0 | D73: =C73 -> 0 | E73: =D73 -> 0
A74: MGO Local | B74: =Purchases!L8 -> 0 | C74: =B74 -> 0 | D74: =C74 -> 0 | E74: =D74 -> 0
A75: MGO Foreign | B75: =Purchases!L9 -> 0 | C75: =B75 -> 0 | D75: =C75 -> 0 | E75: =D75 -> 0
A76: AGO Export | B76: =Purchases!L10 -> 0 | C76: =B76 -> 0 | D76: =C76 -> 0 | E76: =D76 -> 0
A77: AGO Mines | B77: =Purchases!L11 -> 0 | C77: =B77 -> 0 | D77: =C77 -> 0 | E77: =D77 -> 0
A78: ATK | B78: =Purchases!L12 -> 0 | C78: =B78 -> 0 | D78: =C78 -> 0 | E78: =D78 -> 0
A79: LPG | B79: =Purchases!L15 -> 0 | C79: =B79 -> 0 | D79: =C79 -> 0 | E79: =D79 -> 0
A81: Exchange Rate | B81: 14.5
A83: COST OF SALES | B83: 2026 Q1 | C83: 2026 Q2 | D83: 2026 Q3 | E83: 2026 Q4
A84: Gasoline PMS 95 | B84: =[1]Volumes!C53/B61*B72*$B$81 -> #DIV/0! | C84: =[1]Volumes!D53/C61*C72*$B$81 -> #DIV/0! | D84: =[1]Volumes!E53/D61*D72*$B$81 -> #DIV/0! | E84: =[1]Volumes!F53/E61*E72*$B$81 -> #DIV/0!
A85: Gasoil | B85: =[1]Volumes!C54/B62*B73*$B$81 -> #DIV/0! | C85: =[1]Volumes!D54/C62*C73*$B$81 -> #DIV/0! | D85: =[1]Volumes!E54/D62*D73*$B$81 -> #DIV/0! | E85: =[1]Volumes!F54/E62*E73*$B$81 -> #DIV/0!
A86: MGO Local | B86: =[1]Volumes!C55/B63*B74*$B$81 -> #DIV/0! | C86: =[1]Volumes!D55/C63*C74*$B$81 -> #DIV/0! | D86: =[1]Volumes!E55/D63*D74*$B$81 -> #DIV/0! | E86: =[1]Volumes!F55/E63*E74*$B$81 -> #DIV/0!
A87: MGO Foreign | B87: =[1]Volumes!C56/B64*B75*$B$81 -> #DIV/0! | C87: =[1]Volumes!D56/C64*C75*$B$81 -> #DIV/0! | D87: =[1]Volumes!E56/D64*D75*$B$81 -> #DIV/0! | E87: =[1]Volumes!F56/E64*E75*$B$81 -> #DIV/0!
A88: AGO Export | B88: =[1]Volumes!C57/B65*B76*$B$81 -> #DIV/0! | C88: =[1]Volumes!D57/C65*C76*$B$81 -> #DIV/0! | D88: =[1]Volumes!E57/D65*D76*$B$81 -> #DIV/0! | E88: =[1]Volumes!F57/E65*E76*$B$81 -> #DIV/0!
A89: AGO Mines | B89: =[1]Volumes!C58/B66*B77*$B$81 -> #DIV/0! | C89: =[1]Volumes!D58/C66*C77*$B$81 -> #DIV/0! | D89: =[1]Volumes!E58/D66*D77*$B$81 -> #DIV/0! | E89: =[1]Volumes!F58/E66*E77*$B$81 -> #DIV/0!
A90: ATK | B90: =[1]Volumes!C59/B67*B78*$B$81 -> #DIV/0! | C90: =[1]Volumes!D59/C67*C78*$B$81 -> #DIV/0! | D90: =[1]Volumes!E59/D67*D78*$B$81 -> #DIV/0! | E90: =[1]Volumes!F59/E67*E78*$B$81 -> #DIV/0!
A91: LPG | B91: =[1]Volumes!C60/B68*B79*$B$81 -> #DIV/0! | C91: =[1]Volumes!D60/C68*C79*$B$81 -> #DIV/0! | D91: =[1]Volumes!E60/D68*D79*$B$81 -> #DIV/0! | E91: =[1]Volumes!F60/E68*E79*$B$81 -> #DIV/0!
A92: TOTAL | B92: =SUM(B84:B91) -> #DIV/0! | C92: =SUM(C84:C91) -> #DIV/0! | D92: =SUM(D84:D91) -> #DIV/0! | E92: =SUM(E84:E91) -> #DIV/0!
